onmargPy/__init__.py
onmargPy/dataDownload.py
onmargPy-0.1.4.dist-info/LICENSE
onmargPy-0.1.4.dist-info/METADATA
onmargPy-0.1.4.dist-info/WHEEL
onmargPy-0.1.4.dist-info/top_level.txt
onmargPy-0.1.4.dist-info/RECORD
