Metadata-Version: 2.1
Name: onmargPy
Version: 0.1.4
Summary: Python package implementing functions from the onmaRg package for R
Home-page: UNKNOWN
Author: William Conley
Author-email: <william@cconley.ca>
License: UNKNOWN
Keywords: python,data,onmarg,Ontario Marginalization Index,Public Health Ontario
Platform: UNKNOWN
Classifier: Development Status :: 1 - Planning
Classifier: Intended Audience :: Developers
Classifier: Programming Language :: Python :: 3
Classifier: Operating System :: Unix
Classifier: Operating System :: MacOS :: MacOS X
Classifier: Operating System :: Microsoft :: Windows
Requires-Dist: geopandas
Requires-Dist: pandas
